optibot/__init__.py
optibot/core/__init__.py
optibot/core/constants.py
optibot/core/errors.py
optibot/core/optibot.py
optibot/core/renderer.py
optibot/core/script.py
optibot/core/splinter.py
optibot-0.0.2.dist-info/METADATA
optibot-0.0.2.dist-info/WHEEL
optibot-0.0.2.dist-info/top_level.txt
optibot-0.0.2.dist-info/RECORD
